Lab2/mux.v
// output is A (when control == 0) or B (when control == 1)
module mux2(out, A, B, control);
    output out;
    input  A, B;
    input  control;
    wire   wA, wB, not_control;

    not n1(not_control, control);
    and a1(wA, A, not_control);
    and a2(wB, B, control);
    or  o1(out, wA, wB);
endmodule // mux2

// output is A (when control == 00) or B (when control == 01) or
//           C (when control == 10) or D (when control == 11)
module mux4(out, A, B, C, D, control);
    output      out;
    input       A, B, C, D;
    input [1:0] control;
    wire wA, wB, wC, wD, w0, w1;

    not n1(w0, control[0]);
    not n2(w1, control[1]);
    and a1(wA, A, w0, w1);
    and a2(wB, B, control[0], w1);
    and a3(wC, C, w0, control[1]);
    and a4(wD, D, control[0], control[1]);
    or o1(out, wA, wB, wC, wD);
endmodule // mux4

Lab2/logicunit.v
// 00 -> AND, 01 -> OR, 10 -> NOR, 11 -> XOR
module logicunit(out, A, B, control);
    output      out;
    input       A, B;
    input [1:0] control;
    wire w0, w1, AND, OR, NOR, XOR, wA, wO, wN, wX, w2, w3, w4, not_A, not_B, w5;

    not n1(w0, control[0]);
    not n2(w1, control[1]);
    not n3(not_A, A);
    not n4(not_B, B);
    and a0(wA, A, B, w0, w1);
    and a1(OR, control[0], w1);
    or o4(w5, A, B);
    and a2(wO, OR, w5);
    and a3(NOR, w0, control[1]);
    and a4(wN, NOR, not_A, not_B);
    and a5(XOR, control[0], control[1]);
    and a6(w3, A, not_B);
    and a7(w4, B, not_A);
    or o8(w2, w3, w4);
    and a8(wX, w2, XOR);
    or o9(out, wA, wO, wN, wX);
endmodule // logicunit

Lab2/alu1.v
module full_adder(sum, cout, a, b, cin);
    output sum, cout;
    input  a, b, cin;
    wire   partial_s, partial_c1, partial_c2;

    xor x0(partial_s, a, b);
    xor x1(sum, partial_s, cin);
    and a0(partial_c1, a, b);
    and a1(partial_c2, partial_s, cin);
    or  o1(cout, partial_c1, partial_c2);
endmodule // full_adder

`define ALU_ADD    3'h2
`define ALU_SUB    3'h3
`define ALU_AND    3'h4
`define ALU_OR     3'h5
`define ALU_NOR    3'h6
`define ALU_XOR    3'h7

// 01x -> arithmetic, 1xx -> logic
module alu1(out, carryout, A, B, carryin, control);
    output      out, carryout;
    input       A, B, carryin;
    input [2:0] control;
    wire w_B, out1, out2, lout, sum;


    full_adder fa(sum, carryout, A, w_B, carryin);
    xor x(w_B, B, control[0]);


    logicunit lu(lout, A, B, control[1:0]);

    mux2 m2(out, sum, lout, control[2]);

endmodule // alu1

Lab2/alu1_tb.v
module alu1_test;
    // exhaustively test your 1-bit ALU implementation by adapting mux4_tb.v

    // cycle through all combinations of A, B, C, D every 16 time units
    reg A = 0;
    always #1 A = !A;
    reg B = 0;
    always #2 B = !B;
    reg C = 0;
    always #4 C = !C;

    reg [2:0] control = 0;

    initial begin
        $dumpfile("alu1.vcd");
        $dumpvars(0, alu1_test);

        // control is initially 0
        # 16 control = 1; // wait 16 time units (why 16?) and then set it to 1
        # 16 control = 2; // wait 16 time units and then set it to 2
        # 16 control = 3; // wait 16 time units and then set it to 3
        # 16 control = 4; // wait 16 time units and then set it to 4
        # 16 control = 5; // wait 16 time units and then set it to 5
        # 16 control = 6; // wait 16 time units and then set it to 6
        # 16 control = 7; // wait 16 time units and then set it to 7

        # 16 $finish; // wait 16 time units and then end the simulation
    end

    wire out, carryout;
    alu1 alu(out, carryout, A, B, C, control);

    // you really should be using gtkwave instead

    initial begin
        $display("A B cin s o cout");
        $monitor("%d %d %d   %d %d %d   (at time %t)", A, B, C, control, out, carryout, $time);
    end

endmodule

Lab2/alu1.vcd
$date
	Sat Sep  7 20:08:11 2019
$end
$version
	Icarus Verilog
$end
$timescale
	1s
$end
$scope module alu1_test $end
$var wire 1 ! out $end
$var wire 1 " carryout $end
$var reg 1 # A $end
$var reg 1 $ B $end
$var reg 1 % C $end
$var reg 3 & control [2:0] $end
$scope module alu $end
$var wire 1 # A $end
$var wire 1 $ B $end
$var wire 1 % carryin $end
$var wire 3 ' control [2:0] $end
$var wire 1 ( w_B $end
$var wire 1 ) sum $end
$var wire 1 ! out $end
$var wire 1 * lout $end
$var wire 1 " carryout $end
$scope module fa $end
$var wire 1 # a $end
$var wire 1 ( b $end
$var wire 1 % cin $end
$var wire 1 " cout $end
$var wire 1 + partial_c1 $end
$var wire 1 , partial_c2 $end
$var wire 1 - partial_s $end
$var wire 1 ) sum $end
$upscope $end
$scope module lu $end
$var wire 1 # A $end
$var wire 1 $ B $end
$var wire 1 . NOR $end
$var wire 1 / OR $end
$var wire 1 0 XOR $end
$var wire 2 1 control [1:0] $end
$var wire 1 2 not_A $end
$var wire 1 3 not_B $end
$var wire 1 * out $end
$var wire 1 4 w0 $end
$var wire 1 5 w1 $end
$var wire 1 6 w2 $end
$var wire 1 7 w3 $end
$var wire 1 8 w4 $end
$var wire 1 9 w5 $end
$var wire 1 : wA $end
$var wire 1 ; wN $end
$var wire 1 < wO $end
$var wire 1 = wX $end
$upscope $end
$scope module m2 $end
$var wire 1 ) A $end
$var wire 1 * B $end
$var wire 1 > control $end
$var wire 1 ? not_control $end
$var wire 1 ! out $end
$var wire 1 @ wA $end
$var wire 1 A wB $end
$upscope $end
$upscope $end
$upscope $end
$enddefinitions $end
#0
$dumpvars
0A
0@
1?
0>
0=
0<
0;
0:
09
08
07
06
15
14
13
12
b0 1
00
0/
0.
0-
0,
0+
0*
0)
0(
b0 '
b0 &
0%
0$
0#
0"
0!
$end
#1
1!
1@
1)
16
1-
02
19
17
1#
#2
18
16
12
07
1(
03
0#
1$
#3
0!
0@
06
0)
1"
08
1*
0-
1+
02
1:
1#
#4
1!
0"
0*
1@
0+
12
0(
13
0:
09
1)
0#
0$
1%
#5
0!
0@
1"
0)
1,
16
1-
02
19
17
1#
#6
18
16
12
07
1(
03
0#
1$
#7
1!
1@
06
1)
0,
08
1*
0-
1+
02
1:
1#
#8
0!
0"
0*
0@
0+
12
0(
13
0:
09
0)
0#
0$
0%
#9
1!
1@
1)
16
1-
02
19
17
1#
#10
18
16
12
07
1(
03
0#
1$
#11
0!
0@
06
0)
1"
08
1*
0-
1+
02
1:
1#
#12
1!
0"
0*
1@
0+
12
0(
13
0:
09
1)
0#
0$
1%
#13
0!
0@
1"
0)
1,
16
1-
02
19
17
1#
#14
18
16
12
07
1(
03
0#
1$
#15
1!
1@
06
1)
0,
08
1*
0-
1+
02
1:
1#
#16
1!
04
1/
0"
0*
1@
1-
0+
12
13
0:
09
1)
b1 1
0#
0$
0%
b1 &
b1 '
#17
0!
0@
1*
0)
1"
1<
16
0-
1+
02
19
17
1#
#18
0"
18
16
0+
12
07
0(
03
0#
1$
#19
1!
1@
06
1)
08
1-
02
1#
#20
0*
0!
0<
0@
1"
12
1(
13
09
0)
1,
0#
0$
1%
#21
1!
1@
1*
1)
0,
1<
16
0-
1+
02
19
17
1#
#22
0"
18
16
0+
12
07
0(
03
0#
1$
#23
0!
0@
1"
06
0)
1,
08
1-
02
1#
#24
0*
1!
0<
1@
0"
12
1(
13
09
1)
0,
0#
0$
0%
#25
0!
0@
1*
0)
1"
1<
16
0-
1+
02
19
17
1#
#26
0"
18
16
0+
12
07
0(
03
0#
1$
#27
1!
1@
06
1)
08
1-
02
1#
#28
0*
0!
0<
0@
1"
12
1(
13
09
0)
1,
0#
0$
1%
#29
1!
1@
1*
1)
0,
1<
16
0-
1+
02
19
17
1#
#30
0"
18
16
0+
12
07
0(
03
0#
1$
#31
0!
0@
1"
06
0)
1,
08
1-
02
1#
#32
1;
1.
1*
0!
14
05
0/
0<
0@
0"
0-
12
13
09
0)
0,
b10 1
0#
0$
0%
b10 &
b10 '
#33
1!
1@
0*
1)
0;
16
1-
02
19
17
1#
#34
18
16
12
07
1(
03
0#
1$
#35
0!
0@
06
0)
1"
08
0-
1+
02
1#
#36
1*
1!
0"
1;
1@
0+
12
0(
13
09
1)
0#
0$
1%
#37
0!
0@
1"
0*
0)
1,
0;
16
1-
02
19
17
1#
#38
18
16
12
07
1(
03
0#
1$
#39
1!
1@
06
1)
0,
08
0-
1+
02
1#
#40
1*
0!
0"
1;
0@
0+
12
0(
13
09
0)
0#
0$
0%
#41
1!
1@
0*
1)
0;
16
1-
02
19
17
1#
#42
18
16
12
07
1(
03
0#
1$
#43
0!
0@
06
0)
1"
08
0-
1+
02
1#
#44
1*
1!
0"
1;
1@
0+
12
0(
13
09
1)
0#
0$
1%
#45
0!
0@
1"
0*
0)
1,
0;
16
1-
02
19
17
1#
#46
18
16
12
07
1(
03
0#
1$
#47
1!
1@
06
1)
0,
08
0-
1+
02
1#
#48
0.
0*
1!
04
10
0"
0;
1@
1-
0+
12
13
09
1)
b11 1
0#
0$
0%
b11 &
b11 '
#49
0!
1*
0@
1=
0)
1"
16
0-
1+
02
19
17
1#
#50
1*
1=
0"
18
16
0+
12
07
0(
03
0#
1$
#51
0*
1!
0=
1@
06
1)
08
1-
02
1#
#52
0!
0@
1"
12
1(
13
09
0)
1,
0#
0$
1%
#53
1!
1*
1@
1=
1)
0,
16
0-
1+
02
19
17
1#
#54
1*
1=
0"
18
16
0+
12
07
0(
03
0#
1$
#55
0*
0!
0=
0@
1"
06
0)
1,
08
1-
02
1#
#56
1!
1@
0"
12
1(
13
09
1)
0,
0#
0$
0%
#57
0!
1*
0@
1=
0)
1"
16
0-
1+
02
19
17
1#
#58
1*
1=
0"
18
16
0+
12
07
0(
03
0#
1$
#59
0*
1!
0=
1@
06
1)
08
1-
02
1#
#60
0!
0@
1"
12
1(
13
09
0)
1,
0#
0$
1%
#61
1!
1*
1@
1=
1)
0,
16
0-
1+
02
19
17
1#
#62
1*
1=
0"
18
16
0+
12
07
0(
03
0#
1$
#63
0*
0!
0=
0@
1"
06
0)
1,
08
1-
02
1#
#64
14
15
00
0"
0?
0-
12
13
09
0)
0,
b0 1
1>
0#
0$
0%
b100 &
b100 '
#65
1)
16
1-
02
19
17
1#
#66
18
16
12
07
1(
03
0#
1$
#67
1!
06
1A
0)
1"
08
1*
0-
1+
02
1:
1#
#68
0!
0A
0"
0*
0+
12
0(
13
0:
09
1)
0#
0$
1%
#69
1"
0)
1,
16
1-
02
19
17
1#
#70
18
16
12
07
1(
03
0#
1$
#71
1!
06
1A
1)
0,
08
1*
0-
1+
02
1:
1#
#72
0!
0A
0"
0*
0+
12
0(
13
0:
09
0)
0#
0$
0%
#73
1)
16
1-
02
19
17
1#
#74
18
16
12
07
1(
03
0#
1$
#75
1!
06
1A
0)
1"
08
1*
0-
1+
02
1:
1#
#76
0!
0A
0"
0*
0+
12
0(
13
0:
09
1)
0#
0$
1%
#77
1"
0)
1,
16
1-
02
19
17
1#
#78
18
16
12
07
1(
03
0#
1$
#79
1!
06
1A
1)
0,
08
1*
0-
1+
02
1:
1#
#80
0!
0A
04
1/
0"
0*
1-
0+
12
13
0:
09
1)
b1 1
0#
0$
0%
b101 &
b101 '
#81
1!
1A
1*
0)
1"
1<
16
0-
1+
02
19
17
1#
#82
0"
18
16
0+
12
07
0(
03
0#
1$
#83
06
1)
08
1-
02
1#
#84
0!
0A
0*
0<
1"
12
1(
13
09
0)
1,
0#
0$
1%
#85
1!
1A
1*
1)
0,
1<
16
0-
1+
02
19
17
1#
#86
0"
18
16
0+
12
07
0(
03
0#
1$
#87
1"
06
0)
1,
08
1-
02
1#
#88
0!
0A
0*
0<
0"
12
1(
13
09
1)
0,
0#
0$
0%
#89
1!
1A
1*
0)
1"
1<
16
0-
1+
02
19
17
1#
#90
0"
18
16
0+
12
07
0(
03
0#
1$
#91
06
1)
08
1-
02
1#
#92
0!
0A
0*
0<
1"
12
1(
13
09
0)
1,
0#
0$
1%
#93
1!
1A
1*
1)
0,
1<
16
0-
1+
02
19
17
1#
#94
0"
18
16
0+
12
07
0(
03
0#
1$
#95
1"
06
0)
1,
08
1-
02
1#
#96
1!
1;
1A
1.
1*
14
05
0/
0<
0"
0-
12
13
09
0)
0,
b10 1
0#
0$
0%
b110 &
b110 '
#97
0!
0A
0*
1)
0;
16
1-
02
19
17
1#
#98
18
16
12
07
1(
03
0#
1$
#99
06
0)
1"
08
0-
1+
02
1#
#100
1!
1A
1*
0"
1;
0+
12
0(
13
09
1)
0#
0$
1%
#101
0!
0A
1"
0*
0)
1,
0;
16
1-
02
19
17
1#
#102
18
16
12
07
1(
03
0#
1$
#103
06
1)
0,
08
0-
1+
02
1#
#104
1!
1A
1*
0"
1;
0+
12
0(
13
09
0)
0#
0$
0%
#105
0!
0A
0*
1)
0;
16
1-
02
19
17
1#
#106
18
16
12
07
1(
03
0#
1$
#107
06
0)
1"
08
0-
1+
02
1#
#108
1!
1A
1*
0"
1;
0+
12
0(
13
09
1)
0#
0$
1%
#109
0!
0A
1"
0*
0)
1,
0;
16
1-
02
19
17
1#
#110
18
16
12
07
1(
03
0#
1$
#111
06
1)
0,
08
0-
1+
02
1#
#112
0!
0A
0.
0*
04
10
0"
0;
1-
0+
12
13
09
1)
b11 1
0#
0$
0%
b111 &
b111 '
#113
1!
1A
1*
1=
0)
1"
16
0-
1+
02
19
17
1#
#114
1!
1A
1*
1=
0"
18
16
0+
12
07
0(
03
0#
1$
#115
0!
0A
0*
0=
06
1)
08
1-
02
1#
#116
1"
12
1(
13
09
0)
1,
0#
0$
1%
#117
1!
1A
1*
1=
1)
0,
16
0-
1+
02
19
17
1#
#118
1!
1A
1*
1=
0"
18
16
0+
12
07
0(
03
0#
1$
#119
0!
0A
0*
0=
1"
06
0)
1,
08
1-
02
1#
#120
0"
12
1(
13
09
1)
0,
0#
0$
0%
#121
1!
1A
1*
1=
0)
1"
16
0-
1+
02
19
17
1#
#122
1!
1A
1*
1=
0"
18
16
0+
12
07
0(
03
0#
1$
#123
0!
0A
0*
0=
06
1)
08
1-
02
1#
#124
1"
12
1(
13
09
0)
1,
0#
0$
1%
#125
1!
1A
1*
1=
1)
0,
16
0-
1+
02
19
17
1#
#126
1!
1A
1*
1=
0"
18
16
0+
12
07
0(
03
0#
1$
#127
0!
0A
0*
0=
1"
06
0)
1,
08
1-
02
1#
#128
0"
12
1(
13
09
1)
0,
0#
0$
0%
