Lab2/logicunit.v
// 00 -> AND, 01 -> OR, 10 -> NOR, 11 -> XOR
module logicunit(out, A, B, control);
    output      out;
    input       A, B;
    input [1:0] control;
    wire w0, w1, AND, OR, NOR, XOR, wA, wO, wN, wX, w2, w3, w4, not_A, not_B, w5;

    not n1(w0, control[0]);
    not n2(w1, control[1]);
    not n3(not_A, A);
    not n4(not_B, B);
    and a0(wA, A, B, w0, w1);
    and a1(OR, control[0], w1);
    or o4(w5, A, B);
    and a2(wO, OR, w5);
    and a3(NOR, w0, control[1]);
    and a4(wN, NOR, not_A, not_B);
    and a5(XOR, control[0], control[1]);
    and a6(w3, A, not_B);
    and a7(w4, B, not_A);
    or o8(w2, w3, w4);
    and a8(wX, w2, XOR);
    or o9(out, wA, wO, wN, wX);
endmodule // logicunit

Lab2/logicunit_tb.v
module logicunit_test;
    // exhaustively test your logic unit implementation by adapting mux4_tb.v
    // cycle through all combinations of A, B, C, D every 16 time units
    reg A = 0;
    always #1 A = !A;
    reg B = 0;
    always #2 B = !B;

    reg [1:0] control = 0;

    initial begin
        $dumpfile("lgu.vcd");
        $dumpvars(0, logicunit_test);

        // control is initially 0
        # 16 control = 1; // wait 16 time units (why 16?) and then set it to 1
        # 16 control = 2; // wait 16 time units and then set it to 2
        # 16 control = 3; // wait 16 time units and then set it to 3
        # 16 $finish; // wait 16 time units and then end the simulation
    end

    wire out;
    logicunit lu(out, A, B, control);

    // you really should be using gtkwave instead

    initial begin
        $display("A B s o");
        $monitor("%d %d %d %d (at time %t)", A, B, control, out, $time);
    end
endmodule // logicunit_test

Lab2/lgu.vcd
$date
	Sat Sep  7 20:08:11 2019
$end
$version
	Icarus Verilog
$end
$timescale
	1s
$end
$scope module logicunit_test $end
$var wire 1 ! out $end
$var reg 1 " A $end
$var reg 1 # B $end
$var reg 2 $ control [1:0] $end
$scope module lu $end
$var wire 1 " A $end
$var wire 1 # B $end
$var wire 1 % NOR $end
$var wire 1 & OR $end
$var wire 1 ' XOR $end
$var wire 2 ( control [1:0] $end
$var wire 1 ) not_A $end
$var wire 1 * not_B $end
$var wire 1 ! out $end
$var wire 1 + w0 $end
$var wire 1 , w1 $end
$var wire 1 - w2 $end
$var wire 1 . w3 $end
$var wire 1 / w4 $end
$var wire 1 0 w5 $end
$var wire 1 1 wA $end
$var wire 1 2 wN $end
$var wire 1 3 wO $end
$var wire 1 4 wX $end
$upscope $end
$upscope $end
$enddefinitions $end
#0
$dumpvars
04
03
02
01
00
0/
0.
0-
1,
1+
1*
1)
b0 (
0'
0&
0%
b0 $
0#
0"
0!
$end
#1
1-
0)
10
1.
1"
#2
1/
1-
1)
0.
0*
0"
1#
#3
0-
0/
1!
0)
11
1"
#4
0!
1)
1*
01
00
0"
0#
#5
1-
0)
10
1.
1"
#6
1/
1-
1)
0.
0*
0"
1#
#7
0-
0/
1!
0)
11
1"
#8
0!
1)
1*
01
00
0"
0#
#9
1-
0)
10
1.
1"
#10
1/
1-
1)
0.
0*
0"
1#
#11
0-
0/
1!
0)
11
1"
#12
0!
1)
1*
01
00
0"
0#
#13
1-
0)
10
1.
1"
#14
1/
1-
1)
0.
0*
0"
1#
#15
0-
0/
1!
0)
11
1"
#16
0!
0+
1&
1)
1*
01
00
0"
0#
b1 $
b1 (
#17
1!
13
1-
0)
10
1.
1"
#18
1/
1-
1)
0.
0*
0"
1#
#19
0-
0/
0)
1"
#20
0!
03
1)
1*
00
0"
0#
#21
1!
13
1-
0)
10
1.
1"
#22
1/
1-
1)
0.
0*
0"
1#
#23
0-
0/
0)
1"
#24
0!
03
1)
1*
00
0"
0#
#25
1!
13
1-
0)
10
1.
1"
#26
1/
1-
1)
0.
0*
0"
1#
#27
0-
0/
0)
1"
#28
0!
03
1)
1*
00
0"
0#
#29
1!
13
1-
0)
10
1.
1"
#30
1/
1-
1)
0.
0*
0"
1#
#31
0-
0/
0)
1"
#32
12
1!
1%
03
1+
0,
0&
1)
1*
00
0"
0#
b10 $
b10 (
#33
0!
02
1-
0)
10
1.
1"
#34
1/
1-
1)
0.
0*
0"
1#
#35
0-
0/
0)
1"
#36
1!
12
1)
1*
00
0"
0#
#37
0!
02
1-
0)
10
1.
1"
#38
1/
1-
1)
0.
0*
0"
1#
#39
0-
0/
0)
1"
#40
1!
12
1)
1*
00
0"
0#
#41
0!
02
1-
0)
10
1.
1"
#42
1/
1-
1)
0.
0*
0"
1#
#43
0-
0/
0)
1"
#44
1!
12
1)
1*
00
0"
0#
#45
0!
02
1-
0)
10
1.
1"
#46
1/
1-
1)
0.
0*
0"
1#
#47
0-
0/
0)
1"
#48
0!
0%
02
0+
1'
1)
1*
00
0"
0#
b11 $
b11 (
#49
1!
14
1-
0)
10
1.
1"
#50
1!
14
1/
1-
1)
0.
0*
0"
1#
#51
0!
04
0-
0/
0)
1"
#52
1)
1*
00
0"
0#
#53
1!
14
1-
0)
10
1.
1"
#54
1!
14
1/
1-
1)
0.
0*
0"
1#
#55
0!
04
0-
0/
0)
1"
#56
1)
1*
00
0"
0#
#57
1!
14
1-
0)
10
1.
1"
#58
1!
14
1/
1-
1)
0.
0*
0"
1#
#59
0!
04
0-
0/
0)
1"
#60
1)
1*
00
0"
0#
#61
1!
14
1-
0)
10
1.
1"
#62
1!
14
1/
1-
1)
0.
0*
0"
1#
#63
0!
04
0-
0/
0)
1"
#64
1)
1*
00
0"
0#
