Lab2/mux.v
// output is A (when control == 0) or B (when control == 1)
module mux2(out, A, B, control);
    output out;
    input  A, B;
    input  control;
    wire   wA, wB, not_control;

    not n1(not_control, control);
    and a1(wA, A, not_control);
    and a2(wB, B, control);
    or  o1(out, wA, wB);
endmodule // mux2

// output is A (when control == 00) or B (when control == 01) or
//           C (when control == 10) or D (when control == 11)
module mux4(out, A, B, C, D, control);
    output      out;
    input       A, B, C, D;
    input [1:0] control;
    wire wA, wB, wC, wD, w0, w1;

    not n1(w0, control[0]);
    not n2(w1, control[1]);
    and a1(wA, A, w0, w1);
    and a2(wB, B, control[0], w1);
    and a3(wC, C, w0, control[1]);
    and a4(wD, D, control[0], control[1]);
    or o1(out, wA, wB, wC, wD);
endmodule // mux4

Lab2/mux4_tb.v
module mux4_test;

    // cycle through all combinations of A, B, C, D every 16 time units
    reg A = 0;
    always #1 A = !A;
    reg B = 0;
    always #2 B = !B;
    reg C = 0;
    always #4 C = !C;
    reg D = 0;
    always #8 D = !D;

    reg [1:0] control = 0;

    initial begin
        $dumpfile("mux4.vcd");
        $dumpvars(0, mux4_test);

        // control is initially 0
        # 16 control = 1; // wait 16 time units (why 16?) and then set it to 1
        # 16 control = 2; // wait 16 time units and then set it to 2
        # 16 control = 3; // wait 16 time units and then set it to 3
        # 16 $finish; // wait 16 time units and then end the simulation
    end

    wire out;
    mux4 m4(out, A, B, C, D, control);

    // you really should be using gtkwave instead

    initial begin
        $display("A B C D s o");
        $monitor("%d %d %d %d %d %d (at time %t)", A, B, C, D, control, out, $time);
    end
    
endmodule // mux4_test

Lab2/mux4.vcd
$date
	Sat Sep  7 20:08:11 2019
$end
$version
	Icarus Verilog
$end
$timescale
	1s
$end
$scope module mux4_test $end
$var wire 1 ! out $end
$var reg 1 " A $end
$var reg 1 # B $end
$var reg 1 $ C $end
$var reg 1 % D $end
$var reg 2 & control [1:0] $end
$scope module m4 $end
$var wire 1 " A $end
$var wire 1 # B $end
$var wire 1 $ C $end
$var wire 1 % D $end
$var wire 2 ' control [1:0] $end
$var wire 1 ! out $end
$var wire 1 ( w0 $end
$var wire 1 ) w1 $end
$var wire 1 * wA $end
$var wire 1 + wB $end
$var wire 1 , wC $end
$var wire 1 - wD $end
$upscope $end
$upscope $end
$enddefinitions $end
#0
$dumpvars
0-
0,
0+
0*
1)
1(
b0 '
b0 &
0%
0$
0#
0"
0!
$end
#1
1!
1*
1"
#2
0!
0*
0"
1#
#3
1!
1*
1"
#4
0!
0*
0"
0#
1$
#5
1!
1*
1"
#6
0!
0*
0"
1#
#7
1!
1*
1"
#8
0!
0*
0"
0#
0$
1%
#9
1!
1*
1"
#10
0!
0*
0"
1#
#11
1!
1*
1"
#12
0!
0*
0"
0#
1$
#13
1!
1*
1"
#14
0!
0*
0"
1#
#15
1!
1*
1"
#16
0!
0(
0*
0"
0#
0$
0%
b1 &
b1 '
#17
1"
#18
1!
1+
0"
1#
#19
1"
#20
0!
0+
0"
0#
1$
#21
1"
#22
1!
1+
0"
1#
#23
1"
#24
0!
0+
0"
0#
0$
1%
#25
1"
#26
1!
1+
0"
1#
#27
1"
#28
0!
0+
0"
0#
1$
#29
1"
#30
1!
1+
0"
1#
#31
1"
#32
0!
1(
0)
0+
0"
0#
0$
0%
b10 &
b10 '
#33
1"
#34
0"
1#
#35
1"
#36
1!
1,
0"
0#
1$
#37
1"
#38
0"
1#
#39
1"
#40
0!
0,
0"
0#
0$
1%
#41
1"
#42
0"
1#
#43
1"
#44
1!
1,
0"
0#
1$
#45
1"
#46
0"
1#
#47
1"
#48
0!
0(
0,
0"
0#
0$
0%
b11 &
b11 '
#49
1"
#50
0"
1#
#51
1"
#52
0"
0#
1$
#53
1"
#54
0"
1#
#55
1"
#56
1!
1-
0"
0#
0$
1%
#57
1"
#58
0"
1#
#59
1"
#60
0"
0#
1$
#61
1"
#62
0"
1#
#63
1"
#64
0!
0-
0"
0#
0$
0%
